am_keyman/__init__.py
am_keyman/main.py
am_keyman/user_auth.html
am_keyman-0.1.6.dist-info/METADATA
am_keyman-0.1.6.dist-info/WHEEL
am_keyman-0.1.6.dist-info/entry_points.txt
am_keyman-0.1.6.dist-info/top_level.txt
am_keyman-0.1.6.dist-info/RECORD
