Metadata-Version: 2.4
Name: am-keyman
Version: 0.1.6
Author-email: Sergio Mattei <sergiomattei@outlook.com>
Requires-Python: <4.0,>=3.9
Requires-Dist: PyJWT<3.0.0,>=2.8.0
Requires-Dist: click<9.0.0,>=8.1.7
Requires-Dist: rich<14.0.0,>=13.7.0
Requires-Dist: requests<3.0.0,>=2.31.0
Requires-Dist: cryptography<42.0.0,>=41.0.7
Requires-Dist: flask<4.0.0,>=3.0.0
